ratisbona_fanedit/__init__.py
ratisbona_fanedit/__main__.py
ratisbona_fanedit/_fanedit2.py
ratisbona_fanedit/resources/__init__.py
ratisbona_fanedit-0.0.1.dist-info/METADATA
ratisbona_fanedit-0.0.1.dist-info/WHEEL
ratisbona_fanedit-0.0.1.dist-info/entry_points.txt
ratisbona_fanedit-0.0.1.dist-info/licenses/LICENSE
ratisbona_fanedit-0.0.1.dist-info/RECORD
