Metadata-Version: 2.4
Name: ratisbona_fanedit
Version: 0.0.1
Summary: An circular editor for microwave usb pov display fans.
Author-email: Ulrich Schwenk <ulrich-schwenk@gmx.de>
License-File: LICENSE
Classifier: License :: OSI Approved :: GNU General Public License v2 (GPLv2)
Classifier: Operating System :: OS Independent
Classifier: Programming Language :: Python :: 3
Requires-Python: >=3.10
Requires-Dist: click
Requires-Dist: pyqt6
Provides-Extra: dev
Requires-Dist: black; extra == 'dev'
Requires-Dist: black[d]; extra == 'dev'
Requires-Dist: build; extra == 'dev'
Requires-Dist: coverage; extra == 'dev'
Requires-Dist: mypy; extra == 'dev'
Requires-Dist: poethepoet; extra == 'dev'
Requires-Dist: pylint; extra == 'dev'
Requires-Dist: twine; extra == 'dev'
